LICENSE
MANIFEST.in
README.md
pyproject.toml
setup.py
pynq_alveo_examples/__init__.py
pynq_alveo_examples/notebook_test.py
pynq_alveo_examples.egg-info/PKG-INFO
pynq_alveo_examples.egg-info/SOURCES.txt
pynq_alveo_examples.egg-info/dependency_links.txt
pynq_alveo_examples.egg-info/entry_points.txt
pynq_alveo_examples.egg-info/requires.txt
pynq_alveo_examples.egg-info/top_level.txt
pynq_alveo_examples/notebooks/0_welcome_to_pynq/__init__.py
pynq_alveo_examples/notebooks/0_welcome_to_pynq/alveo.png
pynq_alveo_examples/notebooks/0_welcome_to_pynq/welcome-to-pynq.ipynb
pynq_alveo_examples/notebooks/1_introduction/1-vector-addition.ipynb
pynq_alveo_examples/notebooks/1_introduction/2-vadd-and-vmult.ipynb
pynq_alveo_examples/notebooks/1_introduction/3-exploring-a-bitstream.ipynb
pynq_alveo_examples/notebooks/1_introduction/4-opencl-comparison.ipynb
pynq_alveo_examples/notebooks/1_introduction/intro.xclbin.link
pynq_alveo_examples/notebooks/1_introduction/img/pynq-opencl.png
pynq_alveo_examples/notebooks/1_introduction/img/vadd-vmult.png
pynq_alveo_examples/notebooks/1_introduction/img/vadd.png
pynq_alveo_examples/notebooks/2_kernel_optimization/1-kernel-optimizations.ipynb
pynq_alveo_examples/notebooks/2_kernel_optimization/2-using-streams.ipynb
pynq_alveo_examples/notebooks/2_kernel_optimization/3-memories-and-streams.ipynb
pynq_alveo_examples/notebooks/2_kernel_optimization/kernel_opt.xclbin.link
pynq_alveo_examples/notebooks/2_kernel_optimization/img/overlap.png
pynq_alveo_examples/notebooks/2_kernel_optimization/img/vadd-vmult-streams.png
pynq_alveo_examples/notebooks/2_kernel_optimization/img/vadd-wide.png
pynq_alveo_examples/notebooks/3_advanced_features/1-efficient-accelerator-scheduling.ipynb
pynq_alveo_examples/notebooks/3_advanced_features/2-power-measurement.ipynb
pynq_alveo_examples/notebooks/3_advanced_features/3-live-power-plotting.ipynb
pynq_alveo_examples/notebooks/3_advanced_features/4-multi-device.ipynb
pynq_alveo_examples/notebooks/3_advanced_features/advanced.xclbin.link
pynq_alveo_examples/notebooks/3_advanced_features/img/layout.png
pynq_alveo_examples/notebooks/3_advanced_features/img/layout_shuffle.png
pynq_alveo_examples/notebooks/3_advanced_features/img/schedule_overlap.png
