Metadata-Version: 2.1
Name: pynq-alveo-examples
Version: 1.0.3
Summary: Introductory Examples for using PYNQ with Alveo
Home-page: https://github.com/Xilinx/Alveo-PYNQ
Download-URL: https://github.com/Xilinx/Alveo-PYNQ
Author: Giuseppe Natale
Author-email: pynq_support@xilinx.com
License: Apache License 2.0
Requires-Python: >=3.8.0
License-File: LICENSE
